pyhao/__init__.py
pyhao/__version__.py
pyhao/core.py
pyhao/data.py
pyhao/fanyi.py
pyhao/picture.py
pyhao/speak.py
pyhao/version.py
pyhao/weather.py
pyhao/word.py
pyhao/xinchun.py
pyhao-0.1.9.dist-info/LICENSE
pyhao-0.1.9.dist-info/METADATA
pyhao-0.1.9.dist-info/WHEEL
pyhao-0.1.9.dist-info/top_level.txt
pyhao-0.1.9.dist-info/RECORD
