Metadata-Version: 2.1
Name: pyhao
Version: 0.1.9
Summary: 一个简单，方便的python库！
Home-page: UNKNOWN
Author: 张文昊
Author-email: 198554253@qq.com
License: MIT
Platform: UNKNOWN
Classifier: License :: OSI Approved :: MIT License
Classifier: Programming Language :: Python
Classifier: Programming Language :: Python :: 3
Classifier: Programming Language :: Python :: 3.6
Classifier: Programming Language :: Python :: Implementation :: CPython
Classifier: Programming Language :: Python :: Implementation :: PyPy
Requires-Python: >=3.6.0
License-File: LICENSE
